numpyencoder/__init__.py
numpyencoder/numpyencoder.py
numpyencoder-0.3.2.dist-info/licenses/LICENSE
numpyencoder-0.3.2.dist-info/METADATA
numpyencoder-0.3.2.dist-info/WHEEL
numpyencoder-0.3.2.dist-info/top_level.txt
numpyencoder-0.3.2.dist-info/RECORD
