Metadata-Version: 2.4
Name: numpyencoder
Version: 0.3.2
Summary: Python JSON encoder for handling Numpy data types.
Author-email: "Hunter M. Allen" <allenhm@gmail.com>
License-Expression: MIT
Project-URL: Homepage, https://github.com/hmallen/numpyencoder
Keywords: numpy,json,encoder
Classifier: Programming Language :: Python :: 3
Classifier: Operating System :: OS Independent
Requires-Python: >=3.6
License-File: LICENSE
Requires-Dist: numpy>=1.14.3
Requires-Dist: packaging>=20.0
Dynamic: license-file
